{
  "actas": {
    "total": 491,
    "publicadas": 381,
    "espera": 118,
    "verificacion": 373,
    "inconsistencias": 63,
    "correctas": 318,
    "pendientesVerificacionVisual": 10
  },
  "fecha_corte": "2025-12-03 12:00:00.0",
  "depto_code": "12",
  "depto_name": "LA PAZ",
  "candidatos": [
    {
      "cddto_codigo": "000",
      "cddto_nombres": "MARIO ENRIQUE RIVERA CALLEJAS",
      "cddto_apellidos": "",
      "parpo_id": "0001",
      "parpo_nombre": "PARTIDO DEMOCRATA CRISTIANO DE HONDURAS",
      "parpo_color": "#009F3C",
      "parpo_link_logo": "https://elecciones-hnd-publicacion-prod-us-east-1.s3.us-east-1.amazonaws.com/Logos/Partidos/DC.png?X-Amz-Algorithm=AWS4-HMAC-SHA256&X-Amz-Credential=AKIATNSYFO5EYDYMH46K%2F20251203%2Fus-east-1%2Fs3%2Faws4_request&X-Amz-Date=20251203T175127Z&X-Amz-Expires=7200&X-Amz-SignedHeaders=host&X-Amz-Signature=311faed3360c5ffbf41050ffc237c3136cd3cb856c92bbefa51575dd8548f584",
      "cddto_link_logo": "https://elecciones-hnd-publicacion-prod-us-east-1.s3.us-east-1.amazonaws.com/Logos/Candidatos/000_0001.png?X-Amz-Algorithm=AWS4-HMAC-SHA256&X-Amz-Credential=AKIATNSYFO5EYDYMH46K%2F20251203%2Fus-east-1%2Fs3%2Faws4_request&X-Amz-Date=20251203T175127Z&X-Amz-Expires=7200&X-Amz-SignedHeaders=host&X-Amz-Signature=b8accd1304953c988c2c388471453adc6bbdd02f9fdf0d2b4a0f27a4c0ea4804",
      "votos": 106,
      "integrantes": [],
      "parpo_id_int": 1
    },
    {
      "cddto_codigo": "000",
      "cddto_nombres": "RIXI RAMONA MONCADA GODOY",
      "cddto_apellidos": "",
      "parpo_id": "0002",
      "parpo_nombre": "PARTIDO LIBERTAD Y REFUNDACION",
      "parpo_color": "#ff4800",
      "parpo_link_logo": "https://elecciones-hnd-publicacion-prod-us-east-1.s3.us-east-1.amazonaws.com/Logos/Partidos/PARTIDOLIBERTADYREFUNDACION.png?X-Amz-Algorithm=AWS4-HMAC-SHA256&X-Amz-Credential=AKIATNSYFO5EYDYMH46K%2F20251203%2Fus-east-1%2Fs3%2Faws4_request&X-Amz-Date=20251203T175127Z&X-Amz-Expires=7200&X-Amz-SignedHeaders=host&X-Amz-Signature=bdae0b69817797ac9b66c7e1fe9a89105e211b9cb24ed071b7da56f11255d013",
      "cddto_link_logo": "https://elecciones-hnd-publicacion-prod-us-east-1.s3.us-east-1.amazonaws.com/Logos/Candidatos/000_0002.png?X-Amz-Algorithm=AWS4-HMAC-SHA256&X-Amz-Credential=AKIATNSYFO5EYDYMH46K%2F20251203%2Fus-east-1%2Fs3%2Faws4_request&X-Amz-Date=20251203T175127Z&X-Amz-Expires=7200&X-Amz-SignedHeaders=host&X-Amz-Signature=c14a3c224f4e3fa94ac595bfa6311d2f2d8bae4f6267080df95def3c04d74727",
      "votos": 11856,
      "integrantes": [],
      "parpo_id_int": 2
    },
    {
      "cddto_codigo": "000",
      "cddto_nombres": "JORGE NELSON AVILA GUTIERREZ",
      "cddto_apellidos": "",
      "parpo_id": "0003",
      "parpo_nombre": "PARTIDO INNOVACION Y UNIDAD SOCIAL DEMOCRATA",
      "parpo_color": "#F2A900",
      "parpo_link_logo": "https://elecciones-hnd-publicacion-prod-us-east-1.s3.us-east-1.amazonaws.com/Logos/Partidos/PARTIDOINNOVACIONYUNIDADSOCIALDEM%C3%93CRATA.png?X-Amz-Algorithm=AWS4-HMAC-SHA256&X-Amz-Credential=AKIATNSYFO5EYDYMH46K%2F20251203%2Fus-east-1%2Fs3%2Faws4_request&X-Amz-Date=20251203T175127Z&X-Amz-Expires=7200&X-Amz-SignedHeaders=host&X-Amz-Signature=b66dcd38ec235b1aaa5cbb08c295ee4b82d00ec9490548f2a3cfbd6a89342d9d",
      "cddto_link_logo": "https://elecciones-hnd-publicacion-prod-us-east-1.s3.us-east-1.amazonaws.com/Logos/Candidatos/000_0003.png?X-Amz-Algorithm=AWS4-HMAC-SHA256&X-Amz-Credential=AKIATNSYFO5EYDYMH46K%2F20251203%2Fus-east-1%2Fs3%2Faws4_request&X-Amz-Date=20251203T175127Z&X-Amz-Expires=7200&X-Amz-SignedHeaders=host&X-Amz-Signature=3f2fdaa1272a412e7afe6cc959f0e7f05405623ebc2f15ed640409080cf2877e",
      "votos": 350,
      "integrantes": [],
      "parpo_id_int": 3
    },
    {
      "cddto_codigo": "000",
      "cddto_nombres": "SALVADOR ALEJANDRO CESAR NASRALLA SALUM",
      "cddto_apellidos": "",
      "parpo_id": "0004",
      "parpo_nombre": "PARTIDO LIBERAL DE HONDURAS",
      "parpo_color": "#d42225",
      "parpo_link_logo": "https://elecciones-hnd-publicacion-prod-us-east-1.s3.us-east-1.amazonaws.com/Logos/Partidos/PARTIDOLIBERALDEHONDURAS.png?X-Amz-Algorithm=AWS4-HMAC-SHA256&X-Amz-Credential=AKIATNSYFO5EYDYMH46K%2F20251203%2Fus-east-1%2Fs3%2Faws4_request&X-Amz-Date=20251203T175127Z&X-Amz-Expires=7200&X-Amz-SignedHeaders=host&X-Amz-Signature=95fbb3797d5d07a70943758b44838446874ca57be2e2b8ce56ef0cc18143b5b3",
      "cddto_link_logo": "https://elecciones-hnd-publicacion-prod-us-east-1.s3.us-east-1.amazonaws.com/Logos/Candidatos/000_0004.png?X-Amz-Algorithm=AWS4-HMAC-SHA256&X-Amz-Credential=AKIATNSYFO5EYDYMH46K%2F20251203%2Fus-east-1%2Fs3%2Faws4_request&X-Amz-Date=20251203T175127Z&X-Amz-Expires=7200&X-Amz-SignedHeaders=host&X-Amz-Signature=8ea35e8a6e698380c8ab1bb13ada77ca1e42cc32666e403d86d9bd3e487778e0",
      "votos": 23639,
      "integrantes": [],
      "parpo_id_int": 4
    },
    {
      "cddto_codigo": "000",
      "cddto_nombres": "NASRY JUAN ASFURA ZABLAH",
      "cddto_apellidos": "",
      "parpo_id": "0005",
      "parpo_nombre": "PARTIDO NACIONAL DE HONDURAS",
      "parpo_color": "#0077C8",
      "parpo_link_logo": "https://elecciones-hnd-publicacion-prod-us-east-1.s3.us-east-1.amazonaws.com/Logos/Partidos/PARTIDONACIONALDEHONDURAS.png?X-Amz-Algorithm=AWS4-HMAC-SHA256&X-Amz-Credential=AKIATNSYFO5EYDYMH46K%2F20251203%2Fus-east-1%2Fs3%2Faws4_request&X-Amz-Date=20251203T175127Z&X-Amz-Expires=7200&X-Amz-SignedHeaders=host&X-Amz-Signature=5f5878310216727c641d340de8e2ed3ea8ec8643a123a500efa8a8c768981bf2",
      "cddto_link_logo": "https://elecciones-hnd-publicacion-prod-us-east-1.s3.us-east-1.amazonaws.com/Logos/Candidatos/000_0005.png?X-Amz-Algorithm=AWS4-HMAC-SHA256&X-Amz-Credential=AKIATNSYFO5EYDYMH46K%2F20251203%2Fus-east-1%2Fs3%2Faws4_request&X-Amz-Date=20251203T175127Z&X-Amz-Expires=7200&X-Amz-SignedHeaders=host&X-Amz-Signature=122fd682c1f43de52c4e8e126efa8e0697e5d5d26708a8e7991150f1a5b111f6",
      "votos": 29794,
      "integrantes": [],
      "parpo_id_int": 5
    }
  ]
}