{
  "actas": {
    "pendientesVerificacionVisual": 4386,
    "total": 19167,
    "publicadas": 18698,
    "espera": 489,
    "verificacion": 18678,
    "inconsistencias": 2703,
    "correctas": 15995
  },
  "fecha_corte": "2025-12-08 19:00:00.0",
  "depto_code": "00",
  "depto_name": "TODOS",
  "candidatos": [
    {
      "cddto_nombres": "MARIO ENRIQUE RIVERA CALLEJAS",
      "parpo_nombre": "PARTIDO DEMOCRATA CRISTIANO DE HONDURAS",
      "votos": 5421
    },
    {
      "cddto_nombres": "RIXI RAMONA MONCADA GODOY",
      "parpo_nombre": "PARTIDO LIBERTAD Y REFUNDACION",
      "votos": 609545
    },
    {
      "cddto_nombres": "JORGE NELSON AVILA GUTIERREZ",
      "parpo_nombre": "PARTIDO INNOVACION Y UNIDAD SOCIAL DEMOCRATA",
      "votos": 25182
    },
    {
      "cddto_nombres": "SALVADOR ALEJANDRO CESAR NASRALLA SALUM",
      "parpo_nombre": "PARTIDO LIBERAL DE HONDURAS",
      "votos": 1235545
    },
    {
      "cddto_nombres": "NASRY JUAN ASFURA ZABLAH",
      "parpo_nombre": "PARTIDO NACIONAL DE HONDURAS",
      "votos": 1277709
    }
  ]
}