{
  "actas": {
    "pendientesVerificacionVisual": 128,
    "espera": 304,
    "verificacion": 837,
    "total": 1141,
    "publicadas": 861,
    "correctas": 754,
    "inconsistencias": 107
  },
  "fecha_corte": "2025-12-01 12:26:06.0",
  "depto_code": "03",
  "depto_name": "COMAYAGUA",
  "candidatos": [
    {
      "cddto_nombres": "MARIO ENRIQUE RIVERA CALLEJAS",
      "parpo_nombre": "PARTIDO DEMOCRATA CRISTIANO DE HONDURAS",
      "votos": 247
    },
    {
      "cddto_nombres": "RIXI RAMONA MONCADA GODOY",
      "parpo_nombre": "PARTIDO LIBERTAD Y REFUNDACION",
      "votos": 21722
    },
    {
      "cddto_nombres": "JORGE NELSON AVILA GUTIERREZ",
      "parpo_nombre": "PARTIDO INNOVACION Y UNIDAD SOCIAL DEMOCRATA",
      "votos": 1108
    },
    {
      "cddto_nombres": "SALVADOR ALEJANDRO CESAR NASRALLA SALUM",
      "parpo_nombre": "PARTIDO LIBERAL DE HONDURAS",
      "votos": 58672
    },
    {
      "cddto_nombres": "NASRY JUAN ASFURA ZABLAH",
      "parpo_nombre": "PARTIDO NACIONAL DE HONDURAS",
      "votos": 59755
    }
  ]
}